{
  "compliance_uri": "Fedramp-Control-High/0009", 
  "compliance_control_number": "900000104", 
  "compliance_control_uri": "Fedramp-Control-High/0009/900000104", 
  "Control Name": "CONTINUOUS MONITORING | INDEPENDENT ASSESSMENT", 
  "Control Family": "SECURITY ASSESSMENT AND AUTHORIZATION", 
  "Control Statement": "The organization employs assessors or assessment teams with [Assignment: organization-defined level of independence] to monitor the security controls in the information system on an ongoing basis.Supplemental Guidance:  Organizations can maximize the value of assessments of security controls during the continuous monitoring process by requiring that such assessments be conducted by assessors or assessment teams with appropriate levels of independence based on continuous monitoring strategies. Assessor independence provides a degree of impartiality to the monitoring process. To achieve such impartiality, assessors should not: (i) create a mutual or conflicting interest with the organizations where the assessments are being conducted; (ii) assess their own work; (iii) act as management or employees of the organizations they are serving; or (iv) place themselves in advocacy positions for the organizations acquiring their services.", 
  "control_attributes": {
    "Category": "SECURITY ASSESSMENT AND AUTHORIZATION", 
    "description": "The organization employs assessors or assessment teams with [Assignment: organization-defined level of independence] to monitor the security controls in the information system on an ongoing basis.Supplemental Guidance:  Organizations can maximize the value of assessments of security controls during the continuous monitoring process by requiring that such assessments be conducted by assessors or assessment teams with appropriate levels of independence based on continuous monitoring strategies. Assessor independence provides a degree of impartiality to the monitoring process. To achieve such impartiality, assessors should not: (i) create a mutual or conflicting interest with the organizations where the assessments are being conducted; (ii) assess their own work; (iii) act as management or employees of the organizations they are serving; or (iv) place themselves in advocacy positions for the organizations acquiring their services.", 
    "SelectionParam": "", 
    "FedRampParam": "", 
    "SORTID": "CA-07 (01)", 
    "CNTL NO": "CA-7 (1)", 
    "AdditionalReq": " ", 
    "Control Name": "CONTINUOUS MONITORING | INDEPENDENT ASSESSMENT"
  }, 
  "is_deleted": false, 
  "system_default": true
}