{
  "compliance_uri": "PCI-DSS/0012", 
  "compliance_control_number": "1200000136", 
  "compliance_control_uri": "PCI-DSS/0012/1200000136", 
  "Control Name": "Visitors are authorized before entering, and escorted at all times within, areas where cardholder data is processed or maintained.", 
  "Control Family": "Implement Strong Access Control Measures", 
  "Control Statement": "", 
  "control_attributes": {
    "Goals": "Implement Strong Access Control Measures", 
    "Control": "Visitors are authorized before entering, and escorted at all times within, areas where cardholder data is processed or maintained.", 
    "Requirement": "9.4.1. Restrict physical access to cardholder data"
  }, 
  "is_deleted": false, 
  "system_default": true
}