{
  "compliance_uri": "AC3-v-01/0000",
  "compliance_control_number": "110000545",
  "compliance_control_uri": "AC3-v-01/0000/110000545",
  "Control Name": "SA-10 (2) ALTERNATIVE CONFIGURATION MANAGEMENT PROCESSES",
  "Control Family": "SYSTEM AND SERVICES ACQUISITION",
  "Control Statement": "The organization provides an alternate configuration management process using organizational personnel in the absence of a dedicated developer configuration management team.",
  "control_attributes": {
    "Control Name": "SA-10 (2) ALTERNATIVE CONFIGURATION MANAGEMENT PROCESSES",
    "Control Family": "SYSTEM AND SERVICES ACQUISITION",
    "Control Statement": "The organization provides an alternate configuration management process using organizational personnel in the absence of a dedicated developer configuration management team."
  },
  "control_action_attributes": {
    "nature": "Manual",
    "category": "",
    "action_method": "Policy",
    "purpose": "Preventive",
    "level": "Organization",
    "Control Baseline": "Basic",
    "classification": "Technical"
  },
  "service_resource_mapping": [],
  "control_control_mapping": {
    "compliance_control_mapped_uri": [
      "NIST-SP800-53/0006/600000590"
    ],
    "system_default": true,
    "is_deleted": false
  },
  "control_policy_mapping": {
    "is_deleted": false,
    "is_parameterized": false,
    "policy": []
  },
  "system_default": true,
  "is_deleted": false,
  "mode": "New"
}